{"definitionSchemaVersion":"2.0","availableLanguageIds":["fr_FR"],"successPage":{"body":{},"title":{},"enabled":false},"defaultLanguageId":"fr_FR","fields":[{"dataType":"image","predefinedValue":{"fr_FR":""},"readOnly":false,"label":{"fr_FR":"Image du premier onglet"},"type":"image","showLabel":true,"required":false,"fieldNamespace":"","visibilityExpression":"","indexType":"keyword","repeatable":false,"name":"image1","localizable":true,"fieldReference":"image1","tip":{"fr_FR":""}},{"autocomplete":false,"ddmDataProviderInstanceId":"[]","dataType":"string","predefinedValue":{"fr_FR":""},"tooltip":{"fr_FR":""},"readOnly":false,"label":{"fr_FR":"Titre du premier onglet"},"type":"text","showLabel":true,"required":false,"displayStyle":"singleline","fieldNamespace":"","visibilityExpression":"","indexType":"keyword","ddmDataProviderInstanceOutput":"[]","repeatable":false,"name":"title1","options":[{"reference":"","label":{"fr_FR":"Option"},"value":"Option"}],"localizable":true,"fieldReference":"title1","tip":{"fr_FR":""},"placeholder":{"fr_FR":""},"dataSourceType":"manual"},{"autocomplete":false,"ddmDataProviderInstanceId":"[]","dataType":"string","predefinedValue":{"fr_FR":""},"tooltip":{"fr_FR":""},"readOnly":false,"label":{"fr_FR":"Texte du premier onglet"},"type":"text","showLabel":true,"required":false,"displayStyle":"singleline","fieldNamespace":"","visibilityExpression":"","indexType":"keyword","ddmDataProviderInstanceOutput":"[]","repeatable":false,"name":"text1","options":[{"reference":"","label":{"fr_FR":"Option"},"value":"Option"}],"localizable":true,"fieldReference":"text1","tip":{"fr_FR":""},"placeholder":{"fr_FR":""},"dataSourceType":"manual"},{"autocomplete":false,"ddmDataProviderInstanceId":"[]","dataType":"string","predefinedValue":{"fr_FR":""},"tooltip":{"fr_FR":""},"readOnly":false,"label":{"fr_FR":"Lien du premier onglet"},"type":"text","showLabel":true,"required":false,"displayStyle":"singleline","fieldNamespace":"","visibilityExpression":"","indexType":"keyword","ddmDataProviderInstanceOutput":"[]","repeatable":false,"name":"link1","options":[{"reference":"","label":{"fr_FR":"Option"},"value":"Option"}],"localizable":true,"fieldReference":"link1","tip":{"fr_FR":""},"placeholder":{"fr_FR":""},"dataSourceType":"manual"},{"dataType":"image","predefinedValue":{"fr_FR":""},"readOnly":false,"label":{"fr_FR":"Image du deuxième onglet"},"type":"image","showLabel":true,"required":false,"fieldNamespace":"","visibilityExpression":"","indexType":"keyword","repeatable":false,"name":"image2","localizable":true,"fieldReference":"image2","tip":{"fr_FR":""}},{"autocomplete":false,"ddmDataProviderInstanceId":"[]","dataType":"string","predefinedValue":{"fr_FR":""},"tooltip":{"fr_FR":""},"readOnly":false,"label":{"fr_FR":"Titre du deuxième onglet"},"type":"text","showLabel":true,"required":false,"displayStyle":"singleline","fieldNamespace":"","visibilityExpression":"","indexType":"keyword","ddmDataProviderInstanceOutput":"[]","repeatable":false,"name":"title2","options":[{"reference":"","label":{"fr_FR":"Option"},"value":"Option"}],"localizable":true,"fieldReference":"title2","tip":{"fr_FR":""},"placeholder":{"fr_FR":""},"dataSourceType":"manual"},{"autocomplete":false,"ddmDataProviderInstanceId":"[]","dataType":"string","predefinedValue":{"fr_FR":""},"tooltip":{"fr_FR":""},"readOnly":false,"label":{"fr_FR":"Texte du deuxième onglet"},"type":"text","showLabel":true,"required":false,"displayStyle":"singleline","fieldNamespace":"","visibilityExpression":"","indexType":"keyword","ddmDataProviderInstanceOutput":"[]","repeatable":false,"name":"text2","options":[{"reference":"","label":{"fr_FR":"Option"},"value":"Option"}],"localizable":true,"fieldReference":"text2","tip":{"fr_FR":""},"placeholder":{"fr_FR":""},"dataSourceType":"manual"},{"autocomplete":false,"ddmDataProviderInstanceId":"[]","dataType":"string","predefinedValue":{"fr_FR":""},"tooltip":{"fr_FR":""},"readOnly":false,"label":{"fr_FR":"Lien du deuxième onglet"},"type":"text","showLabel":true,"required":false,"displayStyle":"singleline","fieldNamespace":"","visibilityExpression":"","indexType":"keyword","ddmDataProviderInstanceOutput":"[]","repeatable":false,"name":"link2","options":[{"reference":"","label":{"fr_FR":"Option"},"value":"Option"}],"localizable":true,"fieldReference":"link2","tip":{"fr_FR":""},"placeholder":{"fr_FR":""},"dataSourceType":"manual"},{"dataType":"image","predefinedValue":{"fr_FR":""},"readOnly":false,"label":{"fr_FR":"Image du troisième onglet"},"type":"image","showLabel":true,"required":false,"fieldNamespace":"","visibilityExpression":"","indexType":"keyword","repeatable":false,"name":"image3","localizable":true,"fieldReference":"image3","tip":{"fr_FR":""}},{"autocomplete":false,"ddmDataProviderInstanceId":"[]","dataType":"string","predefinedValue":{"fr_FR":""},"tooltip":{"fr_FR":""},"readOnly":false,"label":{"fr_FR":"Titre du troisième onglet"},"type":"text","showLabel":true,"required":false,"displayStyle":"singleline","fieldNamespace":"","visibilityExpression":"","indexType":"keyword","ddmDataProviderInstanceOutput":"[]","repeatable":false,"name":"title3","options":[{"reference":"","label":{"fr_FR":"Option"},"value":"Option"}],"localizable":true,"fieldReference":"title3","tip":{"fr_FR":""},"placeholder":{"fr_FR":""},"dataSourceType":"manual"},{"autocomplete":false,"ddmDataProviderInstanceId":"[]","dataType":"string","predefinedValue":{"fr_FR":""},"tooltip":{"fr_FR":""},"readOnly":false,"label":{"fr_FR":"Texte du troisième onglet"},"type":"text","showLabel":true,"required":false,"displayStyle":"singleline","fieldNamespace":"","visibilityExpression":"","indexType":"keyword","ddmDataProviderInstanceOutput":"[]","repeatable":false,"name":"text3","options":[{"reference":"","label":{"fr_FR":"Option"},"value":"Option"}],"localizable":true,"fieldReference":"text3","tip":{"fr_FR":""},"placeholder":{"fr_FR":""},"dataSourceType":"manual"},{"autocomplete":false,"ddmDataProviderInstanceId":"[]","dataType":"string","predefinedValue":{"fr_FR":""},"tooltip":{"fr_FR":""},"readOnly":false,"label":{"fr_FR":"Lien du troisième onglet"},"type":"text","showLabel":true,"required":false,"displayStyle":"singleline","fieldNamespace":"","visibilityExpression":"","indexType":"keyword","ddmDataProviderInstanceOutput":"[]","repeatable":false,"name":"link3","options":[{"reference":"","label":{"fr_FR":"Option"},"value":"Option"}],"localizable":true,"fieldReference":"link3","tip":{"fr_FR":""},"placeholder":{"fr_FR":""},"dataSourceType":"manual"}]}