{"definitionSchemaVersion":"2.0","availableLanguageIds":["fr_FR"],"successPage":{"body":{},"title":{},"enabled":false},"defaultLanguageId":"fr_FR","fields":[{"labelAtStructureLevel":true,"ddmStructureLayoutId":"","predefinedValue":{},"ddmStructureId":"","upgradedStructure":false,"readOnly":false,"label":{"fr_FR":"Groupe de champs"},"type":"fieldset","rows":"[{\"columns\":[{\"size\":12,\"fields\":[\"image\"]}]},{\"columns\":[{\"size\":12,\"fields\":[\"date\"]}]},{\"columns\":[{\"size\":12,\"fields\":[\"title\"]}]},{\"columns\":[{\"size\":12,\"fields\":[\"description\"]}]},{\"columns\":[{\"size\":12,\"fields\":[\"url\"]}]}]","collapsible":false,"required":false,"showLabel":true,"nestedFields":[{"dataType":"image","predefinedValue":{"fr_FR":""},"readOnly":false,"label":{"fr_FR":"Image"},"type":"image","required":false,"showLabel":true,"indexType":"none","fieldNamespace":"","visibilityExpression":"","repeatable":false,"name":"image","localizable":true,"fieldReference":"image","tip":{"fr_FR":""}},{"autocomplete":false,"ddmDataProviderInstanceId":"[]","dataType":"string","predefinedValue":{"fr_FR":""},"tooltip":{"fr_FR":""},"readOnly":false,"label":{"fr_FR":"Date"},"type":"text","required":false,"showLabel":true,"displayStyle":"singleline","indexType":"none","fieldNamespace":"","visibilityExpression":"","ddmDataProviderInstanceOutput":"[]","repeatable":false,"name":"date","options":[{"reference":"","label":{"fr_FR":"Option"},"value":"Option"}],"localizable":true,"fieldReference":"date","tip":{"fr_FR":""},"placeholder":{"fr_FR":""},"dataSourceType":"manual"},{"autocomplete":false,"ddmDataProviderInstanceId":"[]","dataType":"string","predefinedValue":{"fr_FR":""},"tooltip":{"fr_FR":""},"readOnly":false,"label":{"fr_FR":"Titre"},"type":"text","required":false,"showLabel":true,"displayStyle":"singleline","indexType":"none","fieldNamespace":"","visibilityExpression":"","ddmDataProviderInstanceOutput":"[]","repeatable":false,"name":"title","options":[{"reference":"","label":{"fr_FR":"Option"},"value":"Option"}],"localizable":true,"fieldReference":"title","tip":{"fr_FR":""},"placeholder":{"fr_FR":""},"dataSourceType":"manual"},{"autocomplete":false,"ddmDataProviderInstanceId":"[]","dataType":"string","predefinedValue":{"fr_FR":""},"tooltip":{"fr_FR":""},"readOnly":false,"label":{"fr_FR":"Description"},"type":"text","required":false,"showLabel":true,"displayStyle":"multiline","indexType":"none","fieldNamespace":"","visibilityExpression":"","ddmDataProviderInstanceOutput":"[]","repeatable":false,"name":"description","options":[{"reference":"","label":{"fr_FR":"Option"},"value":"Option"}],"localizable":true,"fieldReference":"description","tip":{"fr_FR":""},"placeholder":{"fr_FR":""},"dataSourceType":"manual"},{"autocomplete":false,"ddmDataProviderInstanceId":"[]","dataType":"string","predefinedValue":{"fr_FR":""},"tooltip":{"fr_FR":""},"readOnly":false,"label":{"fr_FR":"URL"},"type":"text","required":false,"showLabel":true,"displayStyle":"singleline","indexType":"none","fieldNamespace":"","visibilityExpression":"","ddmDataProviderInstanceOutput":"[]","repeatable":false,"name":"url","options":[{"reference":"","label":{"fr_FR":"Option"},"value":"Option"}],"localizable":true,"fieldReference":"url","tip":{"fr_FR":""},"placeholder":{"fr_FR":""},"dataSourceType":"manual"}],"repeatable":true,"name":"imageFieldSet","localizable":true,"fieldReference":"imageFieldSet","tip":{}}]}